movie_frame_extractor_xethhung12/__init__.py
movie_frame_extractor_xethhung12/extractor.py
movie_frame_extractor_xethhung12/getInfo.py
movie_frame_extractor_xethhung12/main.py
movie_frame_extractor_xethhung12-0.0.4.dist-info/METADATA
movie_frame_extractor_xethhung12-0.0.4.dist-info/WHEEL
movie_frame_extractor_xethhung12-0.0.4.dist-info/entry_points.txt
movie_frame_extractor_xethhung12-0.0.4.dist-info/RECORD
